geospaNN/R.py
geospaNN/__init__.py
geospaNN/main.py
geospaNN/model.py
geospaNN/utils.py
geospaNN/visualize.py
geospann-0.1.9.dist-info/METADATA
geospann-0.1.9.dist-info/WHEEL
geospann-0.1.9.dist-info/licenses/LICENSE
geospann-0.1.9.dist-info/RECORD
