Metadata-Version: 2.4
Name: geospaNN
Version: 0.1.9
Summary: A PyThon implementation of NNGLS
Project-URL: Homepage, https://wentaozhan1998.github.io/geospaNN-doc
Project-URL: Repository, https://github.com/WentaoZhan1998/geospaNN
Project-URL: Issues, https://github.com/WentaoZhan1998/geospaNN/issues
Author-email: Wentao Zhan <wzhan3@jhu.edu>, Abhirup Datta <abhidatta@jhu.edu>
Maintainer-email: Wentao Zhan <wzhan3@jhu.edu>
License-File: LICENSE
Classifier: License :: OSI Approved :: MIT License
Classifier: Natural Language :: English
Classifier: Operating System :: OS Independent
Classifier: Programming Language :: Python :: 3
Classifier: Programming Language :: Python :: 3.10
Classifier: Programming Language :: Python :: 3.11
Classifier: Programming Language :: Python :: 3.12
Classifier: Topic :: Scientific/Engineering :: Mathematics
Requires-Python: >=3.9
Requires-Dist: matplotlib
Requires-Dist: numpy
Requires-Dist: rpy2
Requires-Dist: scikit-learn
Requires-Dist: scipy
Requires-Dist: seaborn
Requires-Dist: torch-geometric>=2.3.0
Requires-Dist: torch-scatter>=2.1.2
Requires-Dist: torch-sparse>=0.6.18
Requires-Dist: torch>=2.0.0
